{
  "generated_at": "2026-06-30T06:20:10+00:00",
  "as_of": "2026-06-29",
  "simulations": 10000,
  "locked": {
    "group_matches": 48,
    "knockout_matches": 2
  },
  "format": "LIVE · conditions on played results; only unplayed fixtures are simulated",
  "teams": [
    {
      "team": "Argentina",
      "group": "J",
      "elo": 2148,
      "played": 2,
      "points": 6,
      "gd": 5,
      "status": "qualified",
      "reach_r32": 1.0,
      "reach_r16": 0.9085,
      "reach_qf": 0.7911,
      "reach_sf": 0.5018,
      "reach_final": 0.3307,
      "win": 0.212
    },
    {
      "team": "England",
      "group": "L",
      "elo": 2038,
      "played": 1,
      "points": 3,
      "gd": 2,
      "status": "qualified",
      "reach_r32": 1.0,
      "reach_r16": 0.8107,
      "reach_qf": 0.6438,
      "reach_sf": 0.3891,
      "reach_final": 0.247,
      "win": 0.149
    },
    {
      "team": "France",
      "group": "I",
      "elo": 2123,
      "played": 1,
      "points": 3,
      "gd": 2,
      "status": "qualified",
      "reach_r32": 0.9999,
      "reach_r16": 0.8695,
      "reach_qf": 0.6863,
      "reach_sf": 0.4161,
      "reach_final": 0.2508,
      "win": 0.1443
    },
    {
      "team": "Spain",
      "group": "H",
      "elo": 2144,
      "played": 2,
      "points": 4,
      "gd": 1,
      "status": "qualified",
      "reach_r32": 1.0,
      "reach_r16": 0.9111,
      "reach_qf": 0.6826,
      "reach_sf": 0.4396,
      "reach_final": 0.2584,
      "win": 0.1384
    },
    {
      "team": "Mexico",
      "group": "A",
      "elo": 1912,
      "played": 3,
      "points": 9,
      "gd": 6,
      "status": "qualified",
      "reach_r32": 1.0,
      "reach_r16": 0.7719,
      "reach_qf": 0.5027,
      "reach_sf": 0.362,
      "reach_final": 0.1918,
      "win": 0.095
    },
    {
      "team": "Morocco",
      "group": "C",
      "elo": 1877,
      "played": 1,
      "points": 1,
      "gd": 0,
      "status": "active",
      "reach_r32": 0.989,
      "reach_r16": 0.7631,
      "reach_qf": 0.4738,
      "reach_sf": 0.2691,
      "reach_final": 0.1217,
      "win": 0.0487
    },
    {
      "team": "Brazil",
      "group": "C",
      "elo": 2031,
      "played": 2,
      "points": 4,
      "gd": 3,
      "status": "qualified",
      "reach_r32": 1.0,
      "reach_r16": 0.7558,
      "reach_qf": 0.4429,
      "reach_sf": 0.2633,
      "reach_final": 0.115,
      "win": 0.0469
    },
    {
      "team": "Norway",
      "group": "I",
      "elo": 1918,
      "played": 2,
      "points": 6,
      "gd": 4,
      "status": "qualified",
      "reach_r32": 1.0,
      "reach_r16": 0.7827,
      "reach_qf": 0.5445,
      "reach_sf": 0.2437,
      "reach_final": 0.101,
      "win": 0.041
    },
    {
      "team": "Colombia",
      "group": "K",
      "elo": 2004,
      "played": 2,
      "points": 6,
      "gd": 3,
      "status": "qualified",
      "reach_r32": 1.0,
      "reach_r16": 0.7777,
      "reach_qf": 0.3107,
      "reach_sf": 0.1374,
      "reach_final": 0.0563,
      "win": 0.0245
    },
    {
      "team": "Netherlands",
      "group": "F",
      "elo": 1980,
      "played": 1,
      "points": 1,
      "gd": 0,
      "status": "active",
      "reach_r32": 0.981,
      "reach_r16": 0.5033,
      "reach_qf": 0.3082,
      "reach_sf": 0.1221,
      "reach_final": 0.0465,
      "win": 0.0173
    },
    {
      "team": "Germany",
      "group": "E",
      "elo": 1908,
      "played": 1,
      "points": 3,
      "gd": 6,
      "status": "qualified",
      "reach_r32": 1.0,
      "reach_r16": 0.6382,
      "reach_qf": 0.3289,
      "reach_sf": 0.1189,
      "reach_final": 0.0466,
      "win": 0.0167
    },
    {
      "team": "Australia",
      "group": "D",
      "elo": 1800,
      "played": 2,
      "points": 4,
      "gd": 2,
      "status": "qualified",
      "reach_r32": 1.0,
      "reach_r16": 0.7398,
      "reach_qf": 0.2337,
      "reach_sf": 0.1009,
      "reach_final": 0.0434,
      "win": 0.0154
    },
    {
      "team": "Japan",
      "group": "F",
      "elo": 1888,
      "played": 2,
      "points": 4,
      "gd": 4,
      "status": "qualified",
      "reach_r32": 1.0,
      "reach_r16": 0.7395,
      "reach_qf": 0.3258,
      "reach_sf": 0.1408,
      "reach_final": 0.0518,
      "win": 0.0139
    },
    {
      "team": "Switzerland",
      "group": "B",
      "elo": 1914,
      "played": 3,
      "points": 7,
      "gd": 4,
      "status": "qualified",
      "reach_r32": 1.0,
      "reach_r16": 0.7139,
      "reach_qf": 0.1948,
      "reach_sf": 0.0723,
      "reach_final": 0.0248,
      "win": 0.0073
    },
    {
      "team": "Ivory Coast",
      "group": "E",
      "elo": 1743,
      "played": 2,
      "points": 6,
      "gd": 3,
      "status": "qualified",
      "reach_r32": 1.0,
      "reach_r16": 0.5353,
      "reach_qf": 0.2079,
      "reach_sf": 0.0622,
      "reach_final": 0.0168,
      "win": 0.0055
    },
    {
      "team": "Portugal",
      "group": "K",
      "elo": 1990,
      "played": 1,
      "points": 1,
      "gd": 0,
      "status": "active",
      "reach_r32": 0.8411,
      "reach_r16": 0.274,
      "reach_qf": 0.1252,
      "reach_sf": 0.0423,
      "reach_final": 0.0163,
      "win": 0.0054
    },
    {
      "team": "Belgium",
      "group": "G",
      "elo": 1884,
      "played": 2,
      "points": 4,
      "gd": 4,
      "status": "qualified",
      "reach_r32": 1.0,
      "reach_r16": 0.587,
      "reach_qf": 0.2144,
      "reach_sf": 0.0665,
      "reach_final": 0.0197,
      "win": 0.0053
    },
    {
      "team": "Ecuador",
      "group": "E",
      "elo": 1902,
      "played": 2,
      "points": 1,
      "gd": -1,
      "status": "active",
      "reach_r32": 0.2605,
      "reach_r16": 0.1199,
      "reach_qf": 0.0474,
      "reach_sf": 0.0199,
      "reach_final": 0.0075,
      "win": 0.0027
    },
    {
      "team": "Austria",
      "group": "J",
      "elo": 1836,
      "played": 2,
      "points": 4,
      "gd": 2,
      "status": "qualified",
      "reach_r32": 1.0,
      "reach_r16": 0.2102,
      "reach_qf": 0.1093,
      "reach_sf": 0.0328,
      "reach_final": 0.0091,
      "win": 0.002
    },
    {
      "team": "Egypt",
      "group": "G",
      "elo": 1742,
      "played": 3,
      "points": 5,
      "gd": 2,
      "status": "qualified",
      "reach_r32": 1.0,
      "reach_r16": 0.3881,
      "reach_qf": 0.1038,
      "reach_sf": 0.0303,
      "reach_final": 0.0067,
      "win": 0.0016
    },
    {
      "team": "Algeria",
      "group": "J",
      "elo": 1785,
      "played": 3,
      "points": 4,
      "gd": -2,
      "status": "qualified",
      "reach_r32": 1.0,
      "reach_r16": 0.2909,
      "reach_qf": 0.0693,
      "reach_sf": 0.0178,
      "reach_final": 0.0053,
      "win": 0.0013
    },
    {
      "team": "Uruguay",
      "group": "H",
      "elo": 1841,
      "played": 2,
      "points": 1,
      "gd": -1,
      "status": "active",
      "reach_r32": 0.4502,
      "reach_r16": 0.2412,
      "reach_qf": 0.0568,
      "reach_sf": 0.0125,
      "reach_final": 0.0034,
      "win": 0.0011
    },
    {
      "team": "Croatia",
      "group": "L",
      "elo": 1905,
      "played": 1,
      "points": 0,
      "gd": -2,
      "status": "active",
      "reach_r32": 0.6967,
      "reach_r16": 0.1877,
      "reach_qf": 0.0661,
      "reach_sf": 0.0223,
      "reach_final": 0.0067,
      "win": 0.0011
    },
    {
      "team": "Scotland",
      "group": "C",
      "elo": 1745,
      "played": 1,
      "points": 3,
      "gd": 1,
      "status": "active",
      "reach_r32": 0.9563,
      "reach_r16": 0.3105,
      "reach_qf": 0.0916,
      "reach_sf": 0.0239,
      "reach_final": 0.0056,
      "win": 0.0009
    },
    {
      "team": "United States",
      "group": "D",
      "elo": 1781,
      "played": 2,
      "points": 3,
      "gd": 2,
      "status": "active",
      "reach_r32": 0.9989,
      "reach_r16": 0.2628,
      "reach_qf": 0.0525,
      "reach_sf": 0.0155,
      "reach_final": 0.0031,
      "win": 0.0008
    },
    {
      "team": "Paraguay",
      "group": "D",
      "elo": 1823,
      "played": 3,
      "points": 4,
      "gd": -2,
      "status": "qualified",
      "reach_r32": 1.0,
      "reach_r16": 0.2509,
      "reach_qf": 0.0595,
      "reach_sf": 0.018,
      "reach_final": 0.0043,
      "win": 0.0008
    },
    {
      "team": "Sweden",
      "group": "F",
      "elo": 1742,
      "played": 1,
      "points": 3,
      "gd": 4,
      "status": "qualified",
      "reach_r32": 0.9993,
      "reach_r16": 0.2153,
      "reach_qf": 0.0633,
      "reach_sf": 0.0163,
      "reach_final": 0.0023,
      "win": 0.0003
    },
    {
      "team": "DR Congo",
      "group": "K",
      "elo": 1712,
      "played": 2,
      "points": 1,
      "gd": -1,
      "status": "active",
      "reach_r32": 0.5304,
      "reach_r16": 0.1079,
      "reach_qf": 0.0336,
      "reach_sf": 0.0063,
      "reach_final": 0.0016,
      "win": 0.0003
    },
    {
      "team": "Canada",
      "group": "B",
      "elo": 1764,
      "played": 3,
      "points": 4,
      "gd": 5,
      "status": "qualified",
      "reach_r32": 1.0,
      "reach_r16": 0.5857,
      "reach_qf": 0.0887,
      "reach_sf": 0.0132,
      "reach_final": 0.0021,
      "win": 0.0002
    },
    {
      "team": "South Korea",
      "group": "A",
      "elo": 1723,
      "played": 3,
      "points": 3,
      "gd": -1,
      "status": "active",
      "reach_r32": 0.8452,
      "reach_r16": 0.0882,
      "reach_qf": 0.0186,
      "reach_sf": 0.0035,
      "reach_final": 0.0005,
      "win": 0.0001
    },
    {
      "team": "Senegal",
      "group": "I",
      "elo": 1842,
      "played": 2,
      "points": 0,
      "gd": -3,
      "status": "active",
      "reach_r32": 0.253,
      "reach_r16": 0.0409,
      "reach_qf": 0.0157,
      "reach_sf": 0.0031,
      "reach_final": 0.0007,
      "win": 0.0001
    },
    {
      "team": "Ghana",
      "group": "L",
      "elo": 1575,
      "played": 1,
      "points": 3,
      "gd": 1,
      "status": "active",
      "reach_r32": 0.956,
      "reach_r16": 0.1024,
      "reach_qf": 0.0261,
      "reach_sf": 0.0057,
      "reach_final": 0.0009,
      "win": 0.0001
    },
    {
      "team": "South Africa",
      "group": "A",
      "elo": 1559,
      "played": 3,
      "points": 4,
      "gd": -1,
      "status": "qualified",
      "reach_r32": 1.0,
      "reach_r16": 0.1736,
      "reach_qf": 0.0323,
      "reach_sf": 0.0038,
      "reach_final": 0.0004,
      "win": 0.0
    },
    {
      "team": "Czech Republic",
      "group": "A",
      "elo": 1680,
      "played": 3,
      "points": 1,
      "gd": -4,
      "status": "eliminated",
      "reach_r32": 0.0,
      "reach_r16": 0.0,
      "reach_qf": 0.0,
      "reach_sf": 0.0,
      "reach_final": 0.0,
      "win": 0.0
    },
    {
      "team": "Bosnia and Herzegovina",
      "group": "B",
      "elo": 1622,
      "played": 2,
      "points": 1,
      "gd": -3,
      "status": "active",
      "reach_r32": 0.6503,
      "reach_r16": 0.064,
      "reach_qf": 0.0061,
      "reach_sf": 0.0008,
      "reach_final": 0.0003,
      "win": 0.0
    },
    {
      "team": "Qatar",
      "group": "B",
      "elo": 1411,
      "played": 2,
      "points": 1,
      "gd": -6,
      "status": "active",
      "reach_r32": 0.0745,
      "reach_r16": 0.0031,
      "reach_qf": 0.0,
      "reach_sf": 0.0,
      "reach_final": 0.0,
      "win": 0.0
    },
    {
      "team": "Haiti",
      "group": "C",
      "elo": 1517,
      "played": 2,
      "points": 0,
      "gd": -4,
      "status": "active",
      "reach_r32": 0.002,
      "reach_r16": 0.0,
      "reach_qf": 0.0,
      "reach_sf": 0.0,
      "reach_final": 0.0,
      "win": 0.0
    },
    {
      "team": "Turkey",
      "group": "D",
      "elo": 1852,
      "played": 3,
      "points": 3,
      "gd": -2,
      "status": "eliminated",
      "reach_r32": 0.0,
      "reach_r16": 0.0,
      "reach_qf": 0.0,
      "reach_sf": 0.0,
      "reach_final": 0.0,
      "win": 0.0
    },
    {
      "team": "Curaçao",
      "group": "E",
      "elo": 1438,
      "played": 3,
      "points": 1,
      "gd": -8,
      "status": "eliminated",
      "reach_r32": 0.0,
      "reach_r16": 0.0,
      "reach_qf": 0.0,
      "reach_sf": 0.0,
      "reach_final": 0.0,
      "win": 0.0
    },
    {
      "team": "Tunisia",
      "group": "F",
      "elo": 1562,
      "played": 2,
      "points": 0,
      "gd": -8,
      "status": "active",
      "reach_r32": 0.0029,
      "reach_r16": 0.0001,
      "reach_qf": 0.0,
      "reach_sf": 0.0,
      "reach_final": 0.0,
      "win": 0.0
    },
    {
      "team": "Iran",
      "group": "G",
      "elo": 1764,
      "played": 2,
      "points": 2,
      "gd": 0,
      "status": "active",
      "reach_r32": 0.4821,
      "reach_r16": 0.0693,
      "reach_qf": 0.0114,
      "reach_sf": 0.0026,
      "reach_final": 0.0001,
      "win": 0.0
    },
    {
      "team": "New Zealand",
      "group": "G",
      "elo": 1534,
      "played": 3,
      "points": 1,
      "gd": -6,
      "status": "eliminated",
      "reach_r32": 0.0,
      "reach_r16": 0.0,
      "reach_qf": 0.0,
      "reach_sf": 0.0,
      "reach_final": 0.0,
      "win": 0.0
    },
    {
      "team": "Cape Verde",
      "group": "H",
      "elo": 1622,
      "played": 2,
      "points": 2,
      "gd": 0,
      "status": "active",
      "reach_r32": 0.5731,
      "reach_r16": 0.1622,
      "reach_qf": 0.0222,
      "reach_sf": 0.0027,
      "reach_final": 0.0005,
      "win": 0.0
    },
    {
      "team": "Saudi Arabia",
      "group": "H",
      "elo": 1596,
      "played": 2,
      "points": 2,
      "gd": 0,
      "status": "active",
      "reach_r32": 0.1767,
      "reach_r16": 0.0221,
      "reach_qf": 0.0037,
      "reach_sf": 0.0001,
      "reach_final": 0.0,
      "win": 0.0
    },
    {
      "team": "Iraq",
      "group": "I",
      "elo": 1561,
      "played": 1,
      "points": 0,
      "gd": -3,
      "status": "active",
      "reach_r32": 0.0463,
      "reach_r16": 0.0035,
      "reach_qf": 0.0007,
      "reach_sf": 0.0001,
      "reach_final": 0.0001,
      "win": 0.0
    },
    {
      "team": "Jordan",
      "group": "J",
      "elo": 1628,
      "played": 3,
      "points": 0,
      "gd": -5,
      "status": "eliminated",
      "reach_r32": 0.0,
      "reach_r16": 0.0,
      "reach_qf": 0.0,
      "reach_sf": 0.0,
      "reach_final": 0.0,
      "win": 0.0
    },
    {
      "team": "Uzbekistan",
      "group": "K",
      "elo": 1631,
      "played": 1,
      "points": 0,
      "gd": -2,
      "status": "active",
      "reach_r32": 0.1532,
      "reach_r16": 0.0132,
      "reach_qf": 0.0034,
      "reach_sf": 0.0006,
      "reach_final": 0.0002,
      "win": 0.0
    },
    {
      "team": "Panama",
      "group": "L",
      "elo": 1658,
      "played": 1,
      "points": 0,
      "gd": -1,
      "status": "active",
      "reach_r32": 0.0814,
      "reach_r16": 0.0043,
      "reach_qf": 0.0006,
      "reach_sf": 0.0001,
      "reach_final": 0.0,
      "win": 0.0
    }
  ]
}